{
  "configVersion": 1,
  "timestamp": 1714789490757,
  "index": "/index.html",
  "assetGroups": [
    {
      "name": "app",
      "installMode": "prefetch",
      "updateMode": "prefetch",
      "cacheQueryOptions": {
        "ignoreVary": true
      },
      "urls": [
        "/16.b1424cceb03dfaa1.js",
        "/194.fb409c95284fe985.js",
        "/497.89b3db37fc5b9ba8.js",
        "/582.527ca7fb4994b81d.js",
        "/667.108dde1f2cd8a21f.js",
        "/686.12e5ee9be9f55b2c.js",
        "/favicon.ico",
        "/index.html",
        "/main.86299b104f578af6.js",
        "/manifest.webmanifest",
        "/polyfills.3ec6d33af40a9490.js",
        "/runtime.c4a399bb9518bfed.js",
        "/styles.367e0592c0bb21be.css",
        "/sw.js"
      ],
      "patterns": []
    },
    {
      "name": "assets",
      "installMode": "lazy",
      "updateMode": "prefetch",
      "cacheQueryOptions": {
        "ignoreVary": true
      },
      "urls": [
        "/assets/icons/icon-128x128.png",
        "/assets/icons/icon-144x144.png",
        "/assets/icons/icon-152x152.png",
        "/assets/icons/icon-192x192.png",
        "/assets/icons/icon-384x384.png",
        "/assets/icons/icon-512x512.png",
        "/assets/icons/icon-72x72.png",
        "/assets/icons/icon-96x96.png",
        "/assets/logo.png",
        "/assets/saweria.png",
        "/bootstrap-icons.70a9dee9e5ab72aa.woff",
        "/bootstrap-icons.bfa90bda92a84a6a.woff2"
      ],
      "patterns": []
    }
  ],
  "dataGroups": [],
  "hashTable": {
    "/16.b1424cceb03dfaa1.js": "74bc5dc878feae1b733936972576935f9af7b088",
    "/194.fb409c95284fe985.js": "7ba8dff1b036803cbf30cb3f77a7ebdd0a9ad046",
    "/497.89b3db37fc5b9ba8.js": "53e3ff43cc8ad6557ef096bc9d9101051df25fa2",
    "/582.527ca7fb4994b81d.js": "02d3531d53ed7e2f379816f88e9e1e72ac56a1ba",
    "/667.108dde1f2cd8a21f.js": "5d45e190a8b80290e09814d57d1d8dfdb3ff46c5",
    "/686.12e5ee9be9f55b2c.js": "92750c1beb85fd8a30bb04ceb873264d8ff195b8",
    "/assets/icons/icon-128x128.png": "c8b3e94d65b9f791d837a1ff91b16017359e5a97",
    "/assets/icons/icon-144x144.png": "36793df87b7bc09bf9417c0ff2b944fe2558bb58",
    "/assets/icons/icon-152x152.png": "cbfe68b035dcfc8b2572ce541979e496b623e05b",
    "/assets/icons/icon-192x192.png": "3a97f03c5b5c7b7f5ac7b3400aa899ef0aaf2935",
    "/assets/icons/icon-384x384.png": "4383a78393868b37cc52cbb8aaf1317580ca2858",
    "/assets/icons/icon-512x512.png": "52cd7c8f9f1e0ec6a9ab0ce4d7797284cc57dca7",
    "/assets/icons/icon-72x72.png": "ab440f910fa9e362d098d36039fb0e4164bbbb8b",
    "/assets/icons/icon-96x96.png": "86ff8914108ec777a6415c8db80c8f20837bb859",
    "/assets/logo.png": "5fedf156b38675bb09f74d5c714564c3bbf2f089",
    "/assets/saweria.png": "a760b0b7e05e06eaf83d137b4fce885b188903d7",
    "/bootstrap-icons.70a9dee9e5ab72aa.woff": "d5831fd39baf13aff7626e483b9a089730f18604",
    "/bootstrap-icons.bfa90bda92a84a6a.woff2": "020c3c6f9280a315e8425d7f92e15bcd0cdda1b2",
    "/favicon.ico": "0e7bb6cb826cbf9ca9c7f67fd5f36d5e6c9e243b",
    "/index.html": "7f6ca3e8594103aa3c1892b9a8ad44618421f055",
    "/main.86299b104f578af6.js": "2024010aca2d27bc1c01899f5c54350acb65efb4",
    "/manifest.webmanifest": "5eac020e4d6b572d930aa9c7b28ce3d2ae6e593c",
    "/polyfills.3ec6d33af40a9490.js": "11d240916efbc7a65b4b03a79cc3ab183408e571",
    "/runtime.c4a399bb9518bfed.js": "1fa22d141a8788c7b9497f4e8d3fc0c74461b671",
    "/styles.367e0592c0bb21be.css": "6d3e8afcd415aea34e6fbb74d97a0bbd2db00611",
    "/sw.js": "4abebeef51c60f3deae6dbce09b89a8538e0d843"
  },
  "navigationUrls": [
    {
      "positive": true,
      "regex": "^\\/.*$"
    },
    {
      "positive": false,
      "regex": "^\\/(?:.+\\/)?[^/]*\\.[^/]*$"
    },
    {
      "positive": false,
      "regex": "^\\/(?:.+\\/)?[^/]*__[^/]*$"
    },
    {
      "positive": false,
      "regex": "^\\/(?:.+\\/)?[^/]*__[^/]*\\/.*$"
    }
  ],
  "navigationRequestStrategy": "performance"
}